keynote_export/__init__.py
keynote_export/export.py
keynote_export/resources/SanFrancisco-Regular.ttf
keynote_export/resources/presentation.css
keynote_export/resources/share.jinja
keynote_export/resources/site.jinja
keynote_export-0.1.5.dist-info/LICENSE.md
keynote_export-0.1.5.dist-info/METADATA
keynote_export-0.1.5.dist-info/WHEEL
keynote_export-0.1.5.dist-info/entry_points.txt
keynote_export-0.1.5.dist-info/RECORD
